{"nodes": [{"indegree": 4.187354901011057, "group": 2, "name": "10290", "level": 0.0}, {"indegree": 2.6419267958111403, "group": 1, "name": "10511", "level": 0.0}, {"indegree": 2.6419267958111403, "group": 4, "name": "8097", "level": 0.0}, {"indegree": 4.187354901011057, "group": 1, "name": "9289", "level": 0.0}, {"indegree": 2.6419267958111403, "group": 3, "name": "10892", "level": 0.0}, {"indegree": 4.187354901011057, "group": 2, "name": "7512", "level": 0.0}, {"indegree": 5.283853591622281, "group": 4, "name": "7511", "level": 0.0}, {"indegree": 2.6419267958111403, "group": 2, "name": "3851", "level": 0.0}, {"indegree": 2.6419267958111403, "group": 0, "name": "349", "level": 0.0}, {"indegree": 4.187354901011057, "group": 3, "name": "5460", "level": 0.0}, {"indegree": 4.187354901011057, "group": 3, "name": "4964", "level": 0.0}, {"indegree": 4.187354901011057, "group": 4, "name": "10962", "level": 0.0}, {"indegree": 4.187354901011057, "group": 2, "name": "10961", "level": 0.0}, {"indegree": 4.187354901011057, "group": 0, "name": "10960", "level": 0.0}, {"indegree": 9.139565091554182, "group": 2, "name": "6655", "level": 2.0}, {"indegree": 6.1343640518296345, "group": 4, "name": "5304", "level": 1.0}, {"indegree": 2.6419267958111403, "group": 3, "name": "4962", "level": 0.0}, {"indegree": 2.6419267958111403, "group": 1, "name": "10809", "level": 0.0}, {"indegree": 2.6419267958111403, "group": 2, "name": "1665", "level": 0.0}, {"indegree": 2.6419267958111403, "group": 3, "name": "5858", "level": 0.0}, {"indegree": 2.6419267958111403, "group": 2, "name": "591", "level": 0.0}, {"indegree": 2.6419267958111403, "group": 4, "name": "2829", "level": 0.0}, {"indegree": 4.187354901011057, "group": 1, "name": "3384", "level": 0.0}, {"indegree": 4.187354901011057, "group": 2, "name": "8040", "level": 0.0}, {"indegree": 2.6419267958111403, "group": 4, "name": "2443", "level": 0.0}, {"indegree": 2.6419267958111403, "group": 0, "name": "2446", "level": 0.0}, {"indegree": 2.6419267958111403, "group": 4, "name": "10703", "level": 0.0}, {"indegree": 9.471208492633338, "group": 3, "name": "8129", "level": 2.0}, {"indegree": 2.6419267958111403, "group": 1, "name": "8128", "level": 0.0}, {"indegree": 4.187354901011057, "group": 4, "name": "8127", "level": 0.0}, {"indegree": 2.6419267958111403, "group": 2, "name": "8125", "level": 0.0}, {"indegree": 4.187354901011057, "group": 0, "name": "5772", "level": 0.0}, {"indegree": 2.6419267958111403, "group": 0, "name": "8122", "level": 0.0}, {"indegree": 6.1343640518296345, "group": 1, "name": "4353", "level": 1.0}, {"indegree": 2.6419267958111403, "group": 1, "name": "902", "level": 0.0}, {"indegree": 2.6419267958111403, "group": 4, "name": "900", "level": 0.0}, {"indegree": 2.6419267958111403, "group": 2, "name": "906", "level": 0.0}, {"indegree": 4.187354901011057, "group": 0, "name": "907", "level": 0.0}, {"indegree": 4.187354901011057, "group": 1, "name": "904", "level": 0.0}, {"indegree": 2.6419267958111403, "group": 1, "name": "1845", "level": 0.0}, {"indegree": 2.6419267958111403, "group": 4, "name": "1535", "level": 0.0}, {"indegree": 2.6419267958111403, "group": 1, "name": "9414", "level": 0.0}, {"indegree": 2.6419267958111403, "group": 4, "name": "9417", "level": 0.0}, {"indegree": 7.925780387433421, "group": 0, "name": "9418", "level": 1.0}, {"indegree": 2.6419267958111403, "group": 2, "name": "2163", "level": 0.0}, {"indegree": 2.6419267958111403, "group": 0, "name": "10141", "level": 0.0}, {"indegree": 4.187354901011057, "group": 1, "name": "9730", "level": 0.0}, {"indegree": 2.6419267958111403, "group": 2, "name": "9733", "level": 0.0}, {"indegree": 2.6419267958111403, "group": 0, "name": "9732", "level": 0.0}, {"indegree": 6.1343640518296345, "group": 1, "name": "3808", "level": 1.0}, {"indegree": 5.283853591622281, "group": 4, "name": "10147", "level": 0.0}, {"indegree": 9.776290847640775, "group": 3, "name": "9739", "level": 2.0}, {"indegree": 2.6419267958111403, "group": 2, "name": "3804", "level": 0.0}, {"indegree": 4.187354901011057, "group": 1, "name": "3807", "level": 0.0}, {"indegree": 2.6419267958111403, "group": 0, "name": "3806", "level": 0.0}, {"indegree": 2.6419267958111403, "group": 4, "name": "3801", "level": 0.0}, {"indegree": 4.187354901011057, "group": 0, "name": "10799", "level": 0.0}, {"indegree": 8.374709802022114, "group": 4, "name": "8193", "level": 1.0}, {"indegree": 2.6419267958111403, "group": 2, "name": "3518", "level": 0.0}, {"indegree": 2.6419267958111403, "group": 2, "name": "8944", "level": 0.0}, {"indegree": 2.6419267958111403, "group": 1, "name": "859", "level": 0.0}, {"indegree": 4.187354901011057, "group": 1, "name": "10424", "level": 0.0}, {"indegree": 4.187354901011057, "group": 1, "name": "7510", "level": 0.0}, {"indegree": 2.6419267958111403, "group": 0, "name": "8955", "level": 0.0}, {"indegree": 2.6419267958111403, "group": 3, "name": "9741", "level": 0.0}, {"indegree": 2.6419267958111403, "group": 2, "name": "10241", "level": 0.0}, {"indegree": 5.283853591622281, "group": 3, "name": "4070", "level": 0.0}, {"indegree": 2.6419267958111403, "group": 0, "name": "6754", "level": 0.0}, {"indegree": 4.187354901011057, "group": 4, "name": "5797", "level": 0.0}, {"indegree": 2.6419267958111403, "group": 0, "name": "7175", "level": 0.0}, {"indegree": 6.829281696822197, "group": 3, "name": "4611", "level": 1.0}, {"indegree": 2.6419267958111403, "group": 2, "name": "4615", "level": 0.0}, {"indegree": 6.1343640518296345, "group": 4, "name": "5352", "level": 1.0}, {"indegree": 4.187354901011057, "group": 0, "name": "2349", "level": 0.0}, {"indegree": 2.6419267958111403, "group": 1, "name": "5927", "level": 0.0}, {"indegree": 2.6419267958111403, "group": 1, "name": "4882", "level": 0.0}, {"indegree": 9.471208492633338, "group": 0, "name": "9441", "level": 2.0}, {"indegree": 2.6419267958111403, "group": 0, "name": "2469", "level": 0.0}, {"indegree": 2.6419267958111403, "group": 4, "name": "9824", "level": 0.0}, {"indegree": 4.187354901011057, "group": 4, "name": "4915", "level": 0.0}, {"indegree": 10.05875298974742, "group": 0, "name": "9827", "level": 2.0}, {"indegree": 9.471208492633338, "group": 1, "name": "4910", "level": 2.0}, {"indegree": 4.187354901011057, "group": 4, "name": "8649", "level": 0.0}, {"indegree": 4.187354901011057, "group": 1, "name": "8647", "level": 0.0}, {"indegree": 2.6419267958111403, "group": 1, "name": "8644", "level": 0.0}, {"indegree": 2.6419267958111403, "group": 0, "name": "8645", "level": 0.0}, {"indegree": 2.6419267958111403, "group": 4, "name": "8642", "level": 0.0}, {"indegree": 4.187354901011057, "group": 4, "name": "2534", "level": 0.0}, {"indegree": 2.6419267958111403, "group": 4, "name": "8641", "level": 0.0}, {"indegree": 2.6419267958111403, "group": 1, "name": "8111", "level": 0.0}, {"indegree": 2.6419267958111403, "group": 2, "name": "8383", "level": 0.0}, {"indegree": 4.187354901011057, "group": 1, "name": "9363", "level": 0.0}, {"indegree": 4.187354901011057, "group": 3, "name": "8548", "level": 0.0}, {"indegree": 7.925780387433421, "group": 4, "name": "5748", "level": 1.0}, {"indegree": 2.6419267958111403, "group": 4, "name": "9165", "level": 0.0}, {"indegree": 2.6419267958111403, "group": 0, "name": "490", "level": 0.0}, {"indegree": 2.6419267958111403, "group": 2, "name": "3797", "level": 0.0}, {"indegree": 2.6419267958111403, "group": 2, "name": "9689", "level": 0.0}, {"indegree": 2.6419267958111403, "group": 4, "name": "2152", "level": 0.0}, {"indegree": 2.6419267958111403, "group": 3, "name": "10746", "level": 0.0}, {"indegree": 2.6419267958111403, "group": 4, "name": "9683", "level": 0.0}, {"indegree": 11.604181094947336, "group": 2, "name": "10742", "level": 2.0}, {"indegree": 4.187354901011057, "group": 1, "name": "9686", "level": 0.0}, {"indegree": 6.829281696822197, "group": 2, "name": "10525", "level": 1.0}, {"indegree": 2.6419267958111403, "group": 2, "name": "10282", "level": 0.0}, {"indegree": 4.187354901011057, "group": 1, "name": "10887", "level": 0.0}, {"indegree": 2.6419267958111403, "group": 0, "name": "8336", "level": 0.0}, {"indegree": 4.187354901011057, "group": 4, "name": "9702", "level": 0.0}, {"indegree": 4.187354901011057, "group": 4, "name": "9704", "level": 0.0}, {"indegree": 4.187354901011057, "group": 4, "name": "9668", "level": 0.0}, {"indegree": 2.6419267958111403, "group": 1, "name": "9903", "level": 0.0}, {"indegree": 4.187354901011057, "group": 2, "name": "7314", "level": 0.0}, {"indegree": 2.6419267958111403, "group": 2, "name": "10931", "level": 0.0}, {"indegree": 4.187354901011057, "group": 2, "name": "10596", "level": 0.0}, {"indegree": 4.187354901011057, "group": 2, "name": "10595", "level": 0.0}, {"indegree": 4.187354901011057, "group": 3, "name": "9014", "level": 0.0}, {"indegree": 2.6419267958111403, "group": 4, "name": "10263", "level": 0.0}, {"indegree": 2.6419267958111403, "group": 3, "name": "6781", "level": 0.0}, {"indegree": 2.6419267958111403, "group": 1, "name": "6782", "level": 0.0}, {"indegree": 2.6419267958111403, "group": 0, "name": "6666", "level": 0.0}, {"indegree": 2.6419267958111403, "group": 3, "name": "5960", "level": 0.0}, {"indegree": 7.41682619393628, "group": 2, "name": "10870", "level": 1.0}, {"indegree": 2.6419267958111403, "group": 1, "name": "6584", "level": 0.0}, {"indegree": 8.776290847640777, "group": 3, "name": "3744", "level": 1.0}, {"indegree": 2.6419267958111403, "group": 3, "name": "3741", "level": 0.0}, {"indegree": 6.829281696822197, "group": 3, "name": "4542", "level": 1.0}, {"indegree": 2.6419267958111403, "group": 0, "name": "7780", "level": 0.0}, {"indegree": 2.6419267958111403, "group": 0, "name": "2271", "level": 0.0}, {"indegree": 2.6419267958111403, "group": 1, "name": "6732", "level": 0.0}, {"indegree": 6.829281696822197, "group": 0, "name": "5408", "level": 1.0}, {"indegree": 2.6419267958111403, "group": 1, "name": "10906", "level": 0.0}, {"indegree": 2.6419267958111403, "group": 1, "name": "10901", "level": 0.0}, {"indegree": 4.187354901011057, "group": 2, "name": "2379", "level": 0.0}, {"indegree": 2.6419267958111403, "group": 4, "name": "8052", "level": 0.0}, {"indegree": 10.05875298974742, "group": 1, "name": "8505", "level": 2.0}, {"indegree": 2.6419267958111403, "group": 4, "name": "8059", "level": 0.0}, {"indegree": 10.05875298974742, "group": 3, "name": "2456", "level": 2.0}, {"indegree": 8.776290847640777, "group": 2, "name": "8299", "level": 1.0}, {"indegree": 4.187354901011057, "group": 0, "name": "8113", "level": 0.0}, {"indegree": 4.187354901011057, "group": 2, "name": "9875", "level": 0.0}, {"indegree": 2.6419267958111403, "group": 1, "name": "9873", "level": 0.0}, {"indegree": 2.6419267958111403, "group": 4, "name": "8114", "level": 0.0}, {"indegree": 2.6419267958111403, "group": 0, "name": "170", "level": 0.0}, {"indegree": 2.6419267958111403, "group": 3, "name": "4940", "level": 0.0}, {"indegree": 2.6419267958111403, "group": 0, "name": "9402", "level": 0.0}, {"indegree": 2.6419267958111403, "group": 4, "name": "10622", "level": 0.0}, {"indegree": 4.187354901011057, "group": 2, "name": "3081", "level": 0.0}, {"indegree": 2.6419267958111403, "group": 0, "name": "10407", "level": 0.0}, {"indegree": 4.187354901011057, "group": 2, "name": "8574", "level": 0.0}, {"indegree": 4.187354901011057, "group": 0, "name": "9583", "level": 0.0}, {"indegree": 2.6419267958111403, "group": 3, "name": "5896", "level": 0.0}, {"indegree": 2.6419267958111403, "group": 3, "name": "8477", "level": 0.0}, {"indegree": 2.6419267958111403, "group": 4, "name": "9231", "level": 0.0}, {"indegree": 2.6419267958111403, "group": 2, "name": "8472", "level": 0.0}, {"indegree": 8.374709802022114, "group": 1, "name": "8181", "level": 1.0}, {"indegree": 2.6419267958111403, "group": 2, "name": "10496", "level": 0.0}, {"indegree": 11.604181094947336, "group": 1, "name": "10472", "level": 2.0}, {"indegree": 2.6419267958111403, "group": 3, "name": "8320", "level": 0.0}, {"indegree": 5.283853591622281, "group": 0, "name": "9955", "level": 0.0}, {"indegree": 5.283853591622281, "group": 2, "name": "9954", "level": 0.0}, {"indegree": 2.6419267958111403, "group": 1, "name": "9956", "level": 0.0}, {"indegree": 2.6419267958111403, "group": 2, "name": "9951", "level": 0.0}, {"indegree": 2.6419267958111403, "group": 1, "name": "9953", "level": 0.0}, {"indegree": 2.6419267958111403, "group": 2, "name": "9952", "level": 0.0}, {"indegree": 2.6419267958111403, "group": 2, "name": "6138", "level": 0.0}, {"indegree": 6.1343640518296345, "group": 1, "name": "2333", "level": 1.0}, {"indegree": 2.6419267958111403, "group": 1, "name": "7066", "level": 0.0}, {"indegree": 2.6419267958111403, "group": 3, "name": "5931", "level": 0.0}, {"indegree": 2.6419267958111403, "group": 3, "name": "10947", "level": 0.0}, {"indegree": 2.6419267958111403, "group": 0, "name": "5938", "level": 0.0}, {"indegree": 7.41682619393628, "group": 3, "name": "6960", "level": 1.0}, {"indegree": 2.6419267958111403, "group": 4, "name": "1147", "level": 0.0}, {"indegree": 2.6419267958111403, "group": 1, "name": "8627", "level": 0.0}, {"indegree": 2.6419267958111403, "group": 2, "name": "9621", "level": 0.0}, {"indegree": 2.6419267958111403, "group": 4, "name": "2488", "level": 0.0}, {"indegree": 2.6419267958111403, "group": 1, "name": "4901", "level": 0.0}, {"indegree": 2.6419267958111403, "group": 2, "name": "2484", "level": 0.0}, {"indegree": 2.6419267958111403, "group": 2, "name": "2485", "level": 0.0}, {"indegree": 9.471208492633338, "group": 2, "name": "4906", "level": 2.0}, {"indegree": 4.187354901011057, "group": 1, "name": "2665", "level": 0.0}, {"indegree": 4.187354901011057, "group": 2, "name": "10396", "level": 0.0}, {"indegree": 2.6419267958111403, "group": 4, "name": "2466", "level": 0.0}, {"indegree": 4.187354901011057, "group": 4, "name": "10725", "level": 0.0}, {"indegree": 2.6419267958111403, "group": 0, "name": "10724", "level": 0.0}, {"indegree": 2.6419267958111403, "group": 3, "name": "10727", "level": 0.0}, {"indegree": 4.187354901011057, "group": 1, "name": "10720", "level": 0.0}, {"indegree": 2.6419267958111403, "group": 4, "name": "9376", "level": 0.0}, {"indegree": 2.6419267958111403, "group": 0, "name": "6915", "level": 0.0}, {"indegree": 2.6419267958111403, "group": 3, "name": "10688", "level": 0.0}, {"indegree": 2.6419267958111403, "group": 3, "name": "9982", "level": 0.0}, {"indegree": 2.6419267958111403, "group": 1, "name": "6564", "level": 0.0}, {"indegree": 6.1343640518296345, "group": 1, "name": "4978", "level": 1.0}, {"indegree": 2.6419267958111403, "group": 1, "name": "10614", "level": 0.0}, {"indegree": 4.187354901011057, "group": 0, "name": "10617", "level": 0.0}, {"indegree": 2.6419267958111403, "group": 2, "name": "4974", "level": 0.0}, {"indegree": 2.6419267958111403, "group": 0, "name": "4976", "level": 0.0}, {"indegree": 2.6419267958111403, "group": 3, "name": "4977", "level": 0.0}, {"indegree": 7.41682619393628, "group": 3, "name": "6254", "level": 1.0}, {"indegree": 5.283853591622281, "group": 2, "name": "3947", "level": 0.0}, {"indegree": 2.6419267958111403, "group": 2, "name": "9656", "level": 0.0}, {"indegree": 2.6419267958111403, "group": 4, "name": "9712", "level": 0.0}, {"indegree": 2.6419267958111403, "group": 1, "name": "8327", "level": 0.0}, {"indegree": 2.6419267958111403, "group": 0, "name": "8448", "level": 0.0}, {"indegree": 9.471208492633338, "group": 3, "name": "6704", "level": 2.0}, {"indegree": 2.6419267958111403, "group": 4, "name": "834", "level": 0.0}, {"indegree": 2.6419267958111403, "group": 3, "name": "4122", "level": 0.0}, {"indegree": 4.187354901011057, "group": 4, "name": "8886", "level": 0.0}, {"indegree": 2.6419267958111403, "group": 0, "name": "839", "level": 0.0}, {"indegree": 2.6419267958111403, "group": 4, "name": "8968", "level": 0.0}, {"indegree": 7.925780387433421, "group": 0, "name": "7531", "level": 1.0}, {"indegree": 2.6419267958111403, "group": 0, "name": "5682", "level": 0.0}, {"indegree": 2.6419267958111403, "group": 4, "name": "9007", "level": 0.0}, {"indegree": 4.187354901011057, "group": 3, "name": "9006", "level": 0.0}, {"indegree": 2.6419267958111403, "group": 2, "name": "5324", "level": 0.0}, {"indegree": 2.6419267958111403, "group": 2, "name": "6671", "level": 0.0}, {"indegree": 9.139565091554182, "group": 2, "name": "6673", "level": 2.0}, {"indegree": 2.6419267958111403, "group": 4, "name": "381", "level": 0.0}, {"indegree": 2.6419267958111403, "group": 2, "name": "6776", "level": 0.0}, {"indegree": 2.6419267958111403, "group": 0, "name": "6772", "level": 0.0}, {"indegree": 2.6419267958111403, "group": 3, "name": "9963", "level": 0.0}, {"indegree": 2.6419267958111403, "group": 0, "name": "10861", "level": 0.0}, {"indegree": 2.6419267958111403, "group": 2, "name": "10867", "level": 0.0}, {"indegree": 2.6419267958111403, "group": 1, "name": "7900", "level": 0.0}, {"indegree": 2.6419267958111403, "group": 1, "name": "7657", "level": 0.0}, {"indegree": 6.829281696822197, "group": 1, "name": "5430", "level": 1.0}, {"indegree": 2.6419267958111403, "group": 2, "name": "8178", "level": 0.0}, {"indegree": 2.6419267958111403, "group": 2, "name": "10810", "level": 0.0}, {"indegree": 2.6419267958111403, "group": 1, "name": "630", "level": 0.0}, {"indegree": 4.187354901011057, "group": 4, "name": "8064", "level": 0.0}, {"indegree": 9.471208492633338, "group": 3, "name": "9501", "level": 2.0}, {"indegree": 2.6419267958111403, "group": 4, "name": "8108", "level": 0.0}, {"indegree": 2.6419267958111403, "group": 2, "name": "10640", "level": 0.0}, {"indegree": 12.113135288444479, "group": 3, "name": "7486", "level": 2}, {"indegree": 2.6419267958111403, "group": 3, "name": "7482", "level": 0.0}, {"indegree": 10.321718952840692, "group": 2, "name": "4930", "level": 2.0}, {"indegree": 2.6419267958111403, "group": 0, "name": "4932", "level": 0.0}, {"indegree": 4.187354901011057, "group": 2, "name": "4937", "level": 0.0}, {"indegree": 4.187354901011057, "group": 3, "name": "2894", "level": 0.0}, {"indegree": 2.6419267958111403, "group": 0, "name": "7996", "level": 0.0}, {"indegree": 2.6419267958111403, "group": 4, "name": "9707", "level": 0.0}, {"indegree": 2.6419267958111403, "group": 0, "name": "7998", "level": 0.0}, {"indegree": 2.6419267958111403, "group": 3, "name": "8584", "level": 0.0}, {"indegree": 2.6419267958111403, "group": 4, "name": "9345", "level": 0.0}, {"indegree": 2.6419267958111403, "group": 0, "name": "9610", "level": 0.0}, {"indegree": 2.6419267958111403, "group": 0, "name": "9349", "level": 0.0}, {"indegree": 2.6419267958111403, "group": 1, "name": "5881", "level": 0.0}, {"indegree": 2.6419267958111403, "group": 0, "name": "9225", "level": 0.0}, {"indegree": 2.6419267958111403, "group": 0, "name": "6554", "level": 0.0}, {"indegree": 2.6419267958111403, "group": 1, "name": "879", "level": 0.0}, {"indegree": 7.925780387433421, "group": 0, "name": "5722", "level": 1.0}, {"indegree": 2.6419267958111403, "group": 2, "name": "4958", "level": 0.0}, {"indegree": 2.6419267958111403, "group": 4, "name": "7204", "level": 0.0}, {"indegree": 4.187354901011057, "group": 3, "name": "7479", "level": 0.0}, {"indegree": 2.6419267958111403, "group": 3, "name": "7470", "level": 0.0}, {"indegree": 2.6419267958111403, "group": 3, "name": "893", "level": 0.0}, {"indegree": 2.6419267958111403, "group": 2, "name": "894", "level": 0.0}, {"indegree": 2.6419267958111403, "group": 1, "name": "895", "level": 0.0}, {"indegree": 2.6419267958111403, "group": 0, "name": "897", "level": 0.0}, {"indegree": 6.1343640518296345, "group": 0, "name": "5203", "level": 1.0}, {"indegree": 4.187354901011057, "group": 2, "name": "10500", "level": 0.0}, {"indegree": 2.6419267958111403, "group": 3, "name": "6635", "level": 0.0}, {"indegree": 5.283853591622281, "group": 0, "name": "4015", "level": 0.0}, {"indegree": 2.6419267958111403, "group": 0, "name": "9664", "level": 0.0}, {"indegree": 2.6419267958111403, "group": 3, "name": "7509", "level": 0.0}, {"indegree": 4.187354901011057, "group": 3, "name": "3325", "level": 0.0}, {"indegree": 2.6419267958111403, "group": 3, "name": "4007", "level": 0.0}, {"indegree": 2.6419267958111403, "group": 3, "name": "10446", "level": 0.0}, {"indegree": 2.6419267958111403, "group": 0, "name": "10187", "level": 0.0}, {"indegree": 4.187354901011057, "group": 2, "name": "4701", "level": 0.0}, {"indegree": 4.187354901011057, "group": 1, "name": "1778", "level": 0.0}, {"indegree": 2.6419267958111403, "group": 2, "name": "3805", "level": 0.0}, {"indegree": 2.6419267958111403, "group": 4, "name": "10959", "level": 0.0}, {"indegree": 4.187354901011057, "group": 2, "name": "10111", "level": 0.0}, {"indegree": 2.6419267958111403, "group": 1, "name": "10956", "level": 0.0}, {"indegree": 2.6419267958111403, "group": 4, "name": "10957", "level": 0.0}, {"indegree": 2.6419267958111403, "group": 1, "name": "10955", "level": 0.0}, {"indegree": 2.6419267958111403, "group": 3, "name": "8224", "level": 0.0}, {"indegree": 2.6419267958111403, "group": 1, "name": "4338", "level": 0.0}, {"indegree": 6.1343640518296345, "group": 1, "name": "3481", "level": 1.0}, {"indegree": 2.6419267958111403, "group": 0, "name": "8636", "level": 0.0}, {"indegree": 2.6419267958111403, "group": 1, "name": "8633", "level": 0.0}, {"indegree": 4.187354901011057, "group": 2, "name": "2555", "level": 0.0}, {"indegree": 4.187354901011057, "group": 2, "name": "3035", "level": 0.0}, {"indegree": 2.6419267958111403, "group": 3, "name": "2493", "level": 0.0}, {"indegree": 2.6419267958111403, "group": 2, "name": "2492", "level": 0.0}, {"indegree": 8.776290847640777, "group": 4, "name": "8707", "level": 1.0}, {"indegree": 9.139565091554182, "group": 4, "name": "7892", "level": 2.0}, {"indegree": 2.6419267958111403, "group": 2, "name": "2476", "level": 0.0}, {"indegree": 2.6419267958111403, "group": 3, "name": "2475", "level": 0.0}, {"indegree": 10.567707183244561, "group": 2, "name": "10322", "level": 2.0}, {"indegree": 2.6419267958111403, "group": 0, "name": "8030", "level": 0.0}, {"indegree": 2.6419267958111403, "group": 1, "name": "2471", "level": 0.0}, {"indegree": 6.1343640518296345, "group": 0, "name": "10739", "level": 1.0}, {"indegree": 2.6419267958111403, "group": 1, "name": "10736", "level": 0.0}, {"indegree": 2.6419267958111403, "group": 1, "name": "9851", "level": 0.0}, {"indegree": 2.6419267958111403, "group": 3, "name": "117", "level": 0.0}, {"indegree": 4.187354901011057, "group": 4, "name": "6452", "level": 0.0}, {"indegree": 2.6419267958111403, "group": 1, "name": "9147", "level": 0.0}, {"indegree": 4.187354901011057, "group": 2, "name": "7972", "level": 0.0}, {"indegree": 4.187354901011057, "group": 0, "name": "915", "level": 0.0}, {"indegree": 4.187354901011057, "group": 1, "name": "914", "level": 0.0}, {"indegree": 7.925780387433421, "group": 4, "name": "916", "level": 1.0}, {"indegree": 2.6419267958111403, "group": 3, "name": "911", "level": 0.0}, {"indegree": 2.6419267958111403, "group": 2, "name": "910", "level": 0.0}, {"indegree": 6.1343640518296345, "group": 3, "name": "913", "level": 1.0}, {"indegree": 4.187354901011057, "group": 4, "name": "912", "level": 0.0}, {"indegree": 2.6419267958111403, "group": 4, "name": "9728", "level": 0.0}, {"indegree": 2.6419267958111403, "group": 2, "name": "1936", "level": 0.0}, {"indegree": 2.6419267958111403, "group": 2, "name": "10784", "level": 0.0}, {"indegree": 2.6419267958111403, "group": 3, "name": "10422", "level": 0.0}, {"indegree": 4.187354901011057, "group": 1, "name": "10423", "level": 0.0}, {"indegree": 2.6419267958111403, "group": 3, "name": "10420", "level": 0.0}, {"indegree": 2.6419267958111403, "group": 3, "name": "8356", "level": 0.0}, {"indegree": 6.829281696822197, "group": 2, "name": "10425", "level": 1.0}, {"indegree": 2.6419267958111403, "group": 1, "name": "6427", "level": 0.0}, {"indegree": 6.1343640518296345, "group": 1, "name": "5087", "level": 1.0}, {"indegree": 2.6419267958111403, "group": 2, "name": "2674", "level": 0.0}, {"indegree": 2.6419267958111403, "group": 3, "name": "10855", "level": 0.0}, {"indegree": 4.187354901011057, "group": 1, "name": "5943", "level": 0.0}, {"indegree": 2.6419267958111403, "group": 2, "name": "5941", "level": 0.0}, {"indegree": 2.6419267958111403, "group": 1, "name": "4742", "level": 0.0}, {"indegree": 2.6419267958111403, "group": 4, "name": "754", "level": 0.0}, {"indegree": 2.6419267958111403, "group": 4, "name": "5342", "level": 0.0}, {"indegree": 2.6419267958111403, "group": 3, "name": "5427", "level": 0.0}, {"indegree": 2.6419267958111403, "group": 1, "name": "725", "level": 0.0}, {"indegree": 2.6419267958111403, "group": 2, "name": "10927", "level": 0.0}, {"indegree": 2.6419267958111403, "group": 2, "name": "2438", "level": 0.0}, {"indegree": 7.925780387433421, "group": 0, "name": "6493", "level": 1.0}, {"indegree": 2.6419267958111403, "group": 0, "name": "7936", "level": 0.0}, {"indegree": 4.187354901011057, "group": 2, "name": "8071", "level": 0.0}, {"indegree": 2.6419267958111403, "group": 1, "name": "8074", "level": 0.0}, {"indegree": 4.187354901011057, "group": 0, "name": "7839", "level": 0.0}, {"indegree": 2.6419267958111403, "group": 0, "name": "4454", "level": 0.0}, {"indegree": 2.6419267958111403, "group": 3, "name": "3730", "level": 0.0}, {"indegree": 2.6419267958111403, "group": 2, "name": "10773", "level": 0.0}, {"indegree": 11.418217643451916, "group": 3, "name": "10644", "level": 2.0}, {"indegree": 2.6419267958111403, "group": 3, "name": "9427", "level": 0.0}, {"indegree": 2.6419267958111403, "group": 3, "name": "10313", "level": 0.0}, {"indegree": 4.187354901011057, "group": 2, "name": "2723", "level": 0.0}, {"indegree": 2.6419267958111403, "group": 0, "name": "9609", "level": 0.0}, {"indegree": 4.187354901011057, "group": 0, "name": "10315", "level": 0.0}, {"indegree": 9.139565091554182, "group": 4, "name": "8417", "level": 2.0}, {"indegree": 2.6419267958111403, "group": 1, "name": "8998", "level": 0.0}, {"indegree": 2.6419267958111403, "group": 3, "name": "3789", "level": 0.0}, {"indegree": 2.6419267958111403, "group": 1, "name": "829", "level": 0.0}, {"indegree": 2.6419267958111403, "group": 0, "name": "9512", "level": 0.0}, {"indegree": 2.6419267958111403, "group": 1, "name": "7749", "level": 0.0}], "links": [{"source": 108, "target": 286, "value": "1"}, {"source": 102, "target": 286, "value": "1"}, {"source": 149, "target": 286, "value": "1"}, {"source": 286, "target": 108, "value": "1"}, {"source": 286, "target": 102, "value": "1"}, {"source": 286, "target": 100, "value": "1"}, {"source": 286, "target": 149, "value": "1"}, {"source": 286, "target": 211, "value": "1"}, {"source": 286, "target": 27, "value": "1"}, {"source": 286, "target": 127, "value": "1"}, {"source": 56, "target": 203, "value": "1"}, {"source": 182, "target": 203, "value": "1"}, {"source": 259, "target": 203, "value": "1"}, {"source": 272, "target": 203, "value": "1"}, {"source": 212, "target": 203, "value": "1"}, {"source": 298, "target": 203, "value": "1"}, {"source": 203, "target": 182, "value": "1"}, {"source": 203, "target": 259, "value": "1"}, {"source": 203, "target": 272, "value": "1"}, {"source": 203, "target": 212, "value": "1"}, {"source": 203, "target": 298, "value": "1"}, {"source": 315, "target": 121, "value": "1"}, {"source": 315, "target": 193, "value": "1"}, {"source": 315, "target": 309, "value": "1"}, {"source": 315, "target": 118, "value": "1"}, {"source": 72, "target": 167, "value": "1"}, {"source": 72, "target": 10, "value": "1"}, {"source": 72, "target": 16, "value": "1"}, {"source": 72, "target": 270, "value": "1"}, {"source": 0, "target": 215, "value": "1"}, {"source": 109, "target": 215, "value": "1"}, {"source": 91, "target": 215, "value": "1"}, {"source": 148, "target": 215, "value": "1"}, {"source": 23, "target": 215, "value": "1"}, {"source": 215, "target": 0, "value": "1"}, {"source": 215, "target": 109, "value": "1"}, {"source": 215, "target": 91, "value": "1"}, {"source": 215, "target": 148, "value": "1"}, {"source": 215, "target": 23, "value": "1"}, {"source": 296, "target": 125, "value": "1"}, {"source": 125, "target": 188, "value": "1"}, {"source": 125, "target": 296, "value": "1"}, {"source": 125, "target": 146, "value": "1"}, {"source": 146, "target": 125, "value": "1"}, {"source": 339, "target": 14, "value": "1"}, {"source": 186, "target": 14, "value": "1"}, {"source": 115, "target": 14, "value": "1"}, {"source": 153, "target": 14, "value": "1"}, {"source": 240, "target": 14, "value": "1"}, {"source": 14, "target": 105, "value": "1"}, {"source": 14, "target": 115, "value": "1"}, {"source": 14, "target": 253, "value": "1"}, {"source": 14, "target": 245, "value": "1"}, {"source": 14, "target": 227, "value": "1"}, {"source": 276, "target": 278, "value": "1"}, {"source": 268, "target": 278, "value": "1"}, {"source": 278, "target": 201, "value": "1"}, {"source": 278, "target": 268, "value": "1"}, {"source": 179, "target": 27, "value": "1"}, {"source": 179, "target": 28, "value": "1"}, {"source": 274, "target": 178, "value": "1"}, {"source": 273, "target": 178, "value": "1"}, {"source": 275, "target": 178, "value": "1"}, {"source": 4, "target": 178, "value": "1"}, {"source": 90, "target": 178, "value": "1"}, {"source": 247, "target": 178, "value": "1"}, {"source": 68, "target": 178, "value": "1"}, {"source": 178, "target": 68, "value": "1"}, {"source": 178, "target": 176, "value": "1"}, {"source": 178, "target": 73, "value": "1"}, {"source": 73, "target": 178, "value": "1"}, {"source": 112, "target": 165, "value": "1"}, {"source": 130, "target": 165, "value": "1"}, {"source": 322, "target": 165, "value": "1"}, {"source": 165, "target": 1, "value": "1"}, {"source": 209, "target": 65, "value": "1"}, {"source": 209, "target": 158, "value": "1"}, {"source": 209, "target": 83, "value": "1"}, {"source": 209, "target": 2, "value": "1"}, {"source": 209, "target": 6, "value": "1"}, {"source": 209, "target": 174, "value": "1"}, {"source": 209, "target": 34, "value": "1"}, {"source": 56, "target": 136, "value": "1"}, {"source": 267, "target": 136, "value": "1"}, {"source": 189, "target": 136, "value": "1"}, {"source": 345, "target": 136, "value": "1"}, {"source": 92, "target": 136, "value": "1"}, {"source": 312, "target": 136, "value": "1"}, {"source": 223, "target": 136, "value": "1"}, {"source": 251, "target": 136, "value": "1"}, {"source": 187, "target": 136, "value": "1"}, {"source": 164, "target": 136, "value": "1"}, {"source": 213, "target": 136, "value": "1"}, {"source": 265, "target": 136, "value": "1"}, {"source": 136, "target": 194, "value": "1"}, {"source": 266, "target": 8, "value": "1"}, {"source": 261, "target": 27, "value": "1"}, {"source": 261, "target": 214, "value": "1"}, {"source": 261, "target": 38, "value": "1"}, {"source": 17, "target": 81, "value": "1"}, {"source": 183, "target": 81, "value": "1"}, {"source": 113, "target": 81, "value": "1"}, {"source": 107, "target": 81, "value": "1"}, {"source": 63, "target": 81, "value": "1"}, {"source": 330, "target": 81, "value": "1"}, {"source": 135, "target": 81, "value": "1"}, {"source": 111, "target": 81, "value": "1"}, {"source": 81, "target": 113, "value": "1"}, {"source": 81, "target": 107, "value": "1"}, {"source": 81, "target": 111, "value": "1"}, {"source": 66, "target": 218, "value": "1"}, {"source": 66, "target": 53, "value": "1"}, {"source": 66, "target": 142, "value": "1"}, {"source": 289, "target": 221, "value": "1"}, {"source": 289, "target": 220, "value": "1"}, {"source": 289, "target": 308, "value": "1"}, {"source": 289, "target": 334, "value": "1"}, {"source": 289, "target": 193, "value": "1"}, {"source": 289, "target": 310, "value": "1"}, {"source": 289, "target": 116, "value": "1"}, {"source": 289, "target": 306, "value": "1"}, {"source": 289, "target": 144, "value": "1"}, {"source": 289, "target": 208, "value": "1"}, {"source": 289, "target": 27, "value": "1"}, {"source": 289, "target": 230, "value": "1"}, {"source": 289, "target": 263, "value": "1"}, {"source": 289, "target": 177, "value": "1"}, {"source": 289, "target": 25, "value": "1"}, {"source": 198, "target": 279, "value": "1"}, {"source": 198, "target": 27, "value": "1"}, {"source": 198, "target": 49, "value": "1"}, {"source": 15, "target": 340, "value": "1"}, {"source": 15, "target": 48, "value": "1"}, {"source": 15, "target": 89, "value": "1"}, {"source": 15, "target": 5, "value": "1"}, {"source": 226, "target": 232, "value": "1"}, {"source": 199, "target": 232, "value": "1"}, {"source": 336, "target": 232, "value": "1"}, {"source": 152, "target": 232, "value": "1"}, {"source": 280, "target": 232, "value": "1"}, {"source": 157, "target": 232, "value": "1"}, {"source": 225, "target": 232, "value": "1"}, {"source": 238, "target": 232, "value": "1"}, {"source": 346, "target": 232, "value": "1"}, {"source": 232, "target": 141, "value": "1"}, {"source": 232, "target": 5, "value": "1"}, {"source": 232, "target": 236, "value": "1"}, {"source": 232, "target": 291, "value": "1"}, {"source": 232, "target": 77, "value": "1"}, {"source": 232, "target": 304, "value": "1"}, {"source": 120, "target": 232, "value": "1"}, {"source": 236, "target": 232, "value": "1"}, {"source": 320, "target": 232, "value": "1"}, {"source": 205, "target": 232, "value": "1"}, {"source": 7, "target": 232, "value": "1"}, {"source": 58, "target": 232, "value": "1"}, {"source": 316, "target": 232, "value": "1"}, {"source": 171, "target": 232, "value": "1"}, {"source": 237, "target": 319, "value": "1"}, {"source": 237, "target": 175, "value": "1"}, {"source": 154, "target": 121, "value": "1"}, {"source": 154, "target": 99, "value": "1"}, {"source": 154, "target": 43, "value": "1"}, {"source": 154, "target": 94, "value": "1"}, {"source": 154, "target": 27, "value": "1"}, {"source": 154, "target": 191, "value": "1"}, {"source": 154, "target": 71, "value": "1"}, {"source": 154, "target": 277, "value": "1"}, {"source": 140, "target": 70, "value": "1"}, {"source": 244, "target": 70, "value": "1"}, {"source": 70, "target": 311, "value": "1"}, {"source": 70, "target": 210, "value": "1"}, {"source": 70, "target": 344, "value": "1"}, {"source": 285, "target": 105, "value": "1"}, {"source": 285, "target": 239, "value": "1"}, {"source": 285, "target": 151, "value": "1"}, {"source": 285, "target": 27, "value": "1"}, {"source": 285, "target": 133, "value": "1"}, {"source": 285, "target": 62, "value": "1"}, {"source": 285, "target": 119, "value": "1"}, {"source": 285, "target": 190, "value": "1"}, {"source": 285, "target": 323, "value": "1"}, {"source": 294, "target": 216, "value": "1"}, {"source": 11, "target": 134, "value": "1"}, {"source": 12, "target": 134, "value": "1"}, {"source": 13, "target": 134, "value": "1"}, {"source": 271, "target": 134, "value": "1"}, {"source": 114, "target": 134, "value": "1"}, {"source": 134, "target": 11, "value": "1"}, {"source": 134, "target": 12, "value": "1"}, {"source": 134, "target": 13, "value": "1"}, {"source": 134, "target": 121, "value": "1"}, {"source": 134, "target": 114, "value": "1"}, {"source": 134, "target": 314, "value": "1"}, {"source": 134, "target": 324, "value": "1"}, {"source": 134, "target": 20, "value": "1"}, {"source": 317, "target": 234, "value": "1"}, {"source": 231, "target": 234, "value": "1"}, {"source": 145, "target": 234, "value": "1"}, {"source": 180, "target": 234, "value": "1"}, {"source": 219, "target": 234, "value": "1"}, {"source": 78, "target": 234, "value": "1"}, {"source": 200, "target": 234, "value": "1"}, {"source": 88, "target": 234, "value": "1"}, {"source": 166, "target": 234, "value": "1"}, {"source": 31, "target": 234, "value": "1"}, {"source": 234, "target": 180, "value": "1"}, {"source": 234, "target": 31, "value": "1"}, {"source": 234, "target": 301, "value": "1"}, {"source": 332, "target": 234, "value": "1"}, {"source": 101, "target": 168, "value": "1"}, {"source": 101, "target": 325, "value": "1"}, {"source": 101, "target": 121, "value": "1"}, {"source": 101, "target": 103, "value": "1"}, {"source": 101, "target": 243, "value": "1"}, {"source": 101, "target": 41, "value": "1"}, {"source": 101, "target": 242, "value": "1"}, {"source": 101, "target": 172, "value": "1"}, {"source": 101, "target": 202, "value": "1"}, {"source": 101, "target": 27, "value": "1"}, {"source": 101, "target": 233, "value": "1"}, {"source": 101, "target": 191, "value": "1"}, {"source": 101, "target": 10, "value": "1"}, {"source": 101, "target": 143, "value": "1"}, {"source": 101, "target": 96, "value": "1"}, {"source": 101, "target": 124, "value": "1"}, {"source": 101, "target": 304, "value": "1"}, {"source": 101, "target": 255, "value": "1"}, {"source": 101, "target": 321, "value": "1"}, {"source": 101, "target": 295, "value": "1"}, {"source": 335, "target": 131, "value": "1"}, {"source": 335, "target": 121, "value": "1"}, {"source": 335, "target": 292, "value": "1"}, {"source": 335, "target": 103, "value": "1"}, {"source": 335, "target": 313, "value": "1"}, {"source": 335, "target": 61, "value": "1"}, {"source": 335, "target": 50, "value": "1"}, {"source": 335, "target": 158, "value": "1"}, {"source": 335, "target": 47, "value": "1"}, {"source": 335, "target": 83, "value": "1"}, {"source": 335, "target": 85, "value": "1"}, {"source": 335, "target": 9, "value": "1"}, {"source": 335, "target": 195, "value": "1"}, {"source": 335, "target": 283, "value": "1"}, {"source": 335, "target": 181, "value": "1"}, {"source": 335, "target": 301, "value": "1"}, {"source": 335, "target": 305, "value": "1"}, {"source": 335, "target": 302, "value": "1"}, {"source": 9, "target": 335, "value": "1"}, {"source": 40, "target": 110, "value": "1"}, {"source": 57, "target": 313, "value": "1"}, {"source": 57, "target": 97, "value": "1"}, {"source": 57, "target": 82, "value": "1"}, {"source": 57, "target": 27, "value": "1"}, {"source": 57, "target": 6, "value": "1"}, {"source": 57, "target": 343, "value": "1"}, {"source": 57, "target": 288, "value": "1"}, {"source": 57, "target": 254, "value": "1"}, {"source": 80, "target": 121, "value": "1"}, {"source": 80, "target": 45, "value": "1"}, {"source": 80, "target": 59, "value": "1"}, {"source": 80, "target": 228, "value": "1"}, {"source": 80, "target": 222, "value": "1"}, {"source": 80, "target": 67, "value": "1"}, {"source": 80, "target": 169, "value": "1"}, {"source": 80, "target": 191, "value": "1"}, {"source": 80, "target": 44, "value": "1"}, {"source": 80, "target": 301, "value": "1"}, {"source": 80, "target": 299, "value": "1"}, {"source": 80, "target": 248, "value": "1"}, {"source": 228, "target": 80, "value": "1"}, {"source": 297, "target": 93, "value": "1"}, {"source": 138, "target": 93, "value": "1"}, {"source": 69, "target": 93, "value": "1"}, {"source": 93, "target": 104, "value": "1"}, {"source": 93, "target": 138, "value": "1"}, {"source": 93, "target": 128, "value": "1"}, {"source": 93, "target": 24, "value": "1"}, {"source": 3, "target": 341, "value": "1"}, {"source": 341, "target": 155, "value": "1"}, {"source": 341, "target": 43, "value": "1"}, {"source": 341, "target": 3, "value": "1"}, {"source": 341, "target": 290, "value": "1"}, {"source": 341, "target": 49, "value": "1"}, {"source": 341, "target": 264, "value": "1"}, {"source": 341, "target": 301, "value": "1"}, {"source": 341, "target": 300, "value": "1"}, {"source": 264, "target": 341, "value": "1"}, {"source": 26, "target": 249, "value": "1"}, {"source": 249, "target": 260, "value": "1"}, {"source": 249, "target": 269, "value": "1"}, {"source": 249, "target": 37, "value": "1"}, {"source": 249, "target": 95, "value": "1"}, {"source": 21, "target": 249, "value": "1"}, {"source": 269, "target": 249, "value": "1"}, {"source": 137, "target": 184, "value": "1"}, {"source": 137, "target": 192, "value": "1"}, {"source": 137, "target": 147, "value": "1"}, {"source": 137, "target": 329, "value": "1"}, {"source": 137, "target": 122, "value": "1"}, {"source": 137, "target": 98, "value": "1"}, {"source": 137, "target": 39, "value": "1"}, {"source": 137, "target": 60, "value": "1"}, {"source": 329, "target": 137, "value": "1"}, {"source": 139, "target": 33, "value": "1"}, {"source": 33, "target": 139, "value": "1"}, {"source": 33, "target": 27, "value": "1"}, {"source": 33, "target": 326, "value": "1"}, {"source": 282, "target": 292, "value": "1"}, {"source": 282, "target": 313, "value": "1"}, {"source": 170, "target": 43, "value": "1"}, {"source": 170, "target": 86, "value": "1"}, {"source": 170, "target": 30, "value": "1"}, {"source": 170, "target": 6, "value": "1"}, {"source": 170, "target": 305, "value": "1"}, {"source": 170, "target": 257, "value": "1"}, {"source": 129, "target": 43, "value": "1"}, {"source": 129, "target": 150, "value": "1"}, {"source": 129, "target": 79, "value": "1"}, {"source": 129, "target": 301, "value": "1"}, {"source": 79, "target": 129, "value": "1"}, {"source": 252, "target": 327, "value": "1"}, {"source": 327, "target": 29, "value": "1"}, {"source": 327, "target": 252, "value": "1"}, {"source": 327, "target": 318, "value": "1"}, {"source": 327, "target": 196, "value": "1"}, {"source": 327, "target": 49, "value": "1"}, {"source": 318, "target": 327, "value": "1"}, {"source": 224, "target": 50, "value": "1"}, {"source": 224, "target": 43, "value": "1"}, {"source": 224, "target": 74, "value": "1"}, {"source": 224, "target": 22, "value": "1"}, {"source": 22, "target": 224, "value": "1"}, {"source": 76, "target": 293, "value": "1"}, {"source": 76, "target": 103, "value": "1"}, {"source": 76, "target": 310, "value": "1"}, {"source": 76, "target": 160, "value": "1"}, {"source": 76, "target": 159, "value": "1"}, {"source": 76, "target": 43, "value": "1"}, {"source": 76, "target": 117, "value": "1"}, {"source": 76, "target": 54, "value": "1"}, {"source": 76, "target": 333, "value": "1"}, {"source": 76, "target": 284, "value": "1"}, {"source": 76, "target": 301, "value": "1"}, {"source": 18, "target": 53, "value": "1"}, {"source": 258, "target": 340, "value": "1"}, {"source": 258, "target": 304, "value": "1"}, {"source": 258, "target": 38, "value": "1"}, {"source": 258, "target": 207, "value": "1"}, {"source": 185, "target": 156, "value": "1"}, {"source": 156, "target": 292, "value": "1"}, {"source": 156, "target": 185, "value": "1"}, {"source": 156, "target": 313, "value": "1"}, {"source": 156, "target": 61, "value": "1"}, {"source": 156, "target": 159, "value": "1"}, {"source": 156, "target": 43, "value": "1"}, {"source": 156, "target": 206, "value": "1"}, {"source": 156, "target": 82, "value": "1"}, {"source": 156, "target": 331, "value": "1"}, {"source": 156, "target": 191, "value": "1"}, {"source": 156, "target": 75, "value": "1"}, {"source": 156, "target": 55, "value": "1"}, {"source": 156, "target": 132, "value": "1"}, {"source": 156, "target": 301, "value": "1"}, {"source": 156, "target": 299, "value": "1"}, {"source": 156, "target": 303, "value": "1"}, {"source": 206, "target": 156, "value": "1"}, {"source": 331, "target": 156, "value": "1"}, {"source": 132, "target": 156, "value": "1"}, {"source": 51, "target": 292, "value": "1"}, {"source": 51, "target": 103, "value": "1"}, {"source": 51, "target": 313, "value": "1"}, {"source": 51, "target": 159, "value": "1"}, {"source": 51, "target": 163, "value": "1"}, {"source": 51, "target": 42, "value": "1"}, {"source": 51, "target": 27, "value": "1"}, {"source": 51, "target": 328, "value": "1"}, {"source": 51, "target": 49, "value": "1"}, {"source": 51, "target": 287, "value": "1"}, {"source": 51, "target": 300, "value": "1"}, {"source": 51, "target": 36, "value": "1"}, {"source": 281, "target": 337, "value": "1"}, {"source": 281, "target": 162, "value": "1"}, {"source": 126, "target": 197, "value": "1"}, {"source": 197, "target": 342, "value": "1"}, {"source": 197, "target": 29, "value": "1"}, {"source": 197, "target": 62, "value": "1"}, {"source": 197, "target": 19, "value": "1"}, {"source": 197, "target": 235, "value": "1"}, {"source": 87, "target": 103, "value": "1"}, {"source": 87, "target": 241, "value": "1"}, {"source": 338, "target": 92, "value": "1"}, {"source": 338, "target": 204, "value": "1"}, {"source": 229, "target": 50, "value": "1"}, {"source": 229, "target": 158, "value": "1"}, {"source": 229, "target": 161, "value": "1"}, {"source": 229, "target": 84, "value": "1"}, {"source": 229, "target": 32, "value": "1"}, {"source": 229, "target": 217, "value": "1"}, {"source": 229, "target": 250, "value": "1"}, {"source": 229, "target": 52, "value": "1"}, {"source": 229, "target": 37, "value": "1"}, {"source": 229, "target": 35, "value": "1"}, {"source": 229, "target": 256, "value": "1"}, {"source": 64, "target": 123, "value": "1"}, {"source": 46, "target": 123, "value": "1"}, {"source": 262, "target": 123, "value": "1"}, {"source": 173, "target": 123, "value": "1"}, {"source": 246, "target": 123, "value": "1"}, {"source": 106, "target": 123, "value": "1"}, {"source": 123, "target": 46, "value": "1"}, {"source": 123, "target": 304, "value": "1"}, {"source": 307, "target": 123, "value": "1"}]}
